json_converter/__init__.py
json_converter/csv_to_json.py
json_converter/excel_to_json.py
json_ops-0.1.2.dist-info/LICENSE
json_ops-0.1.2.dist-info/METADATA
json_ops-0.1.2.dist-info/WHEEL
json_ops-0.1.2.dist-info/top_level.txt
json_ops-0.1.2.dist-info/RECORD
