Metadata-Version: 2.1
Name: json-ops
Version: 0.1.2
Summary: This is the `json-ops` package, intended to provide a collection of utilities for working with JSON data.
Author-email: Vineet Tiwari <vineettiwari863@gmail.com>
License: MIT License
Classifier: Development Status :: 4 - Beta
Classifier: Intended Audience :: Developers
Classifier: Programming Language :: Python :: 3.12
Classifier: Topic :: Software Development :: Libraries :: Python Modules
Classifier: Topic :: Office/Business :: Financial :: Spreadsheet
Classifier: Topic :: Text Processing :: General
Requires-Python: >=3.12
License-File: LICENSE
Requires-Dist: pytest>=8.3.4
Requires-Dist: pandas>=2.2.3
Requires-Dist: openpyxl>=3.1.5
